TenetPy/PalindromeList.py
TenetPy/PalindromeWord.py
TenetPy/PalindromeWordInList.py
TenetPy/Reverser.py
TenetPy/ReverserList.py
TenetPy/Vowel.py
TenetPy/WordLengthInList.py
TenetPy/__init__.py
TenetPy/main.py
TenetPy-0.4.dist-info/METADATA
TenetPy-0.4.dist-info/WHEEL
TenetPy-0.4.dist-info/top_level.txt
TenetPy-0.4.dist-info/RECORD
